django_atomics/__init__.py
django_atomics/apps.py
django_atomics/base.py
django_atomics/component.py
django_atomics/permissions.py
django_atomics/renderers.py
django_atomics/utils.py
django_atomics/version.py
django_atomics/atoms/__init__.py
django_atomics/atoms/basics.py
django_atomics/atoms/bootstrap.py
django_atomics/atoms/containers.py
django_atomics/atoms/images.py
django_atomics/molecules/__init__.py
django_atomics/molecules/cards.py
django_atomics/organisms/__init__.py
django_atomics/templates/atomics/index.html
django_atomics/templatetags/__init__.py
django_atomics/templatetags/atomics_tags.py
django_atomics-0.0.5.dist-info/LICENCE
django_atomics-0.0.5.dist-info/METADATA
django_atomics-0.0.5.dist-info/WHEEL
django_atomics-0.0.5.dist-info/top_level.txt
django_atomics-0.0.5.dist-info/RECORD
